[
  {
    "text": "welche Pflanze ist das dickste Opfer ich",
    "start": 0.0,
    "duration": 3.419
  },
  {
    "text": "glaube das größte",
    "start": 2.159,
    "duration": 3.74
  },
  {
    "text": "Opfer ist die Nashi Birne",
    "start": 3.419,
    "duration": 6.001
  },
  {
    "text": "das ist so ein random Obst dicker dicker",
    "start": 5.899,
    "duration": 4.541
  },
  {
    "text": "man hat einfach gesagt wir haben den",
    "start": 9.42,
    "duration": 2.219
  },
  {
    "text": "Scheiß Apfel und wir haben eine scheiß",
    "start": 10.44,
    "duration": 2.64
  },
  {
    "text": "Birne wir kreuzen Sie jetzt haben wir",
    "start": 11.639,
    "duration": 3.12
  },
  {
    "text": "Naschi wieso machen die kein cooleres",
    "start": 13.08,
    "duration": 5.04
  },
  {
    "text": "Ort wie Apfel",
    "start": 14.759,
    "duration": 3.361
  }
]