[
  {
    "text": "also ich habe versucht hat extra fit zu",
    "start": 0.0,
    "duration": 3.179
  },
  {
    "text": "klingen am Telefon mir ging es gar nicht",
    "start": 1.8,
    "duration": 2.88
  },
  {
    "text": "bitte in dem Moment Bro ich lag da",
    "start": 3.179,
    "duration": 3.001
  },
  {
    "text": "scheiß gebadet weil die damit dieses",
    "start": 4.68,
    "duration": 4.099
  },
  {
    "text": "Medikament gegeben",
    "start": 6.18,
    "duration": 2.599
  },
  {
    "text": "ja man versucht möglichst nichts stoned",
    "start": 9.26,
    "duration": 4.66
  },
  {
    "text": "auszusehen auf einmal sieht man seine",
    "start": 12.54,
    "duration": 4.28
  },
  {
    "text": "Eltern hallo Frau Müller",
    "start": 13.92,
    "duration": 2.9
  }
]